{
  "Name": "DescribeLiveStreamsFrameRateAndBitRateData",
  "Protocol": "HTTP|HTTPS",
  "Method": "POST|GET",
  "Description": {
    "zh": "实时查询直播流帧率和码率数据。"
  },
  "Parameters": [
    {
      "Name": "AccessKeyId",
      "Position": "Query",
      "Type": "String",
      "Description": {
        "zh": "当认证方式为Accesskey时必填，用户需要显式指定，校验签名使用，不指定则不校验签名"
      },
      "Required": false,
      "Hidden": false,
      "Example": "",
      "SubParameters": null
    },
    {
      "Name": "Action",
      "Position": "Query",
      "Type": "String",
      "Description": {
        "zh": "系统规定参数，取值：DescribeLiveStreamsFrameRateAndBitRateData"
      },
      "Required": false,
      "Hidden": true,
      "Example": "",
      "SubParameters": null
    },
    {
      "Name": "SecurityToken",
      "Position": "Query",
      "Type": "String",
      "Description": {
        "zh": ""
      },
      "Required": false,
      "Hidden": false,
      "Example": "",
      "SubParameters": null
    },
    {
      "Name": "OwnerId",
      "Position": "Query",
      "Type": "Long",
      "Description": {
        "zh": ""
      },
      "Required": false,
      "Hidden": true,
      "Example": "",
      "SubParameters": null
    },
    {
      "Name": "DomainName",
      "Position": "Query",
      "Type": "String",
      "Description": {
        "zh": "您的域名"
      },
      "Required": true,
      "Hidden": false,
      "Example": "",
      "SubParameters": null
    },
    {
      "Name": "AppName",
      "Position": "Query",
      "Type": "String",
      "Description": {
        "zh": "直播流所属应用名称"
      },
      "Required": false,
      "Hidden": false,
      "Example": "",
      "SubParameters": null
    },
    {
      "Name": "StreamName",
      "Position": "Query",
      "Type": "String",
      "Description": {
        "zh": "直播流名称"
      },
      "Required": false,
      "Hidden": false,
      "Example": "",
      "SubParameters": null
    },
    {
      "Name": "StartTime",
      "Position": "Query",
      "Type": "String",
      "Description": {
        "zh": "开始时间，UTC格式, StartTime和EndTime时间间隔在7天内,且EndTime超过当前时间\n"
      },
      "Required": false,
      "Hidden": false,
      "Example": "",
      "SubParameters": null
    },
    {
      "Name": "EndTime",
      "Position": "Query",
      "Type": "String",
      "Description": {
        "zh": "结束时间，UTC格式, StartTime和EndTime时间间隔在7天内,且EndTime超过当前时间\n"
      },
      "Required": false,
      "Hidden": false,
      "Example": "",
      "SubParameters": null
    }
  ],
  "Product": null
}