{
  "Name": "CalculateDBInstanceWeight",
  "Protocol": "HTTP|HTTPS",
  "Method": "POST|GET",
  "Description": {
    "zh": "\n\n查询在系统权重分配方式下，每个实例会被分配的读请求权重值。\n\n实例必须在没有被锁定的情况下才能进行查询，否则操作将会失败。\n\n"
  },
  "Parameters": [
    {
      "Name": "AccessKeyId",
      "Position": "Query",
      "Type": "String",
      "Description": {
        "zh": " 阿里云颁发给用户的访问服务所用的密钥ID。"
      },
      "Required": false,
      "Hidden": false,
      "Example": "",
      "SubParameters": null
    },
    {
      "Name": "AccessKeyId",
      "Position": "Query",
      "Type": "String",
      "Description": {},
      "Required": false,
      "Hidden": false,
      "Example": "",
      "SubParameters": null
    },
    {
      "Name": "Action",
      "Position": "Query",
      "Type": "String",
      "Description": {
        "zh": "系统规定参数，取值：CalculateDBInstanceWeight。"
      },
      "Required": false,
      "Hidden": true,
      "Example": "",
      "SubParameters": null
    },
    {
      "Name": "OwnerId",
      "Position": "Query",
      "Type": "Long",
      "Description": {
        "zh": ""
      },
      "Required": false,
      "Hidden": true,
      "Example": "",
      "SubParameters": null
    },
    {
      "Name": "ResourceOwnerAccount",
      "Position": "Query",
      "Type": "String",
      "Description": {
        "zh": ""
      },
      "Required": false,
      "Hidden": true,
      "Example": "",
      "SubParameters": null
    },
    {
      "Name": "ResourceOwnerId",
      "Position": "Query",
      "Type": "Long",
      "Description": {
        "zh": ""
      },
      "Required": false,
      "Hidden": true,
      "Example": "",
      "SubParameters": null
    },
    {
      "Name": "OwnerAccount",
      "Position": "Query",
      "Type": "String",
      "Description": {
        "zh": "用户主账号。"
      },
      "Required": false,
      "Hidden": true,
      "Example": "",
      "SubParameters": null
    },
    {
      "Name": "DBInstanceId",
      "Position": "Query",
      "Type": "String",
      "Description": {
        "zh": "主实例名。"
      },
      "Required": true,
      "Hidden": false,
      "Example": "",
      "SubParameters": null
    }
  ],
  "Product": null
}