{
  "Name": "ModifyAccountDescription",
  "Protocol": "HTTP|HTTPS",
  "Method": "POST|GET",
  "Description": {
    "zh": "\n修改数据库名的备注名，用于方便用户记录该实例，比如为该实例修改备注名为阿里云测试环境实例账号A。\n  \n"
  },
  "Parameters": [
    {
      "Name": "AccessKeyId",
      "Position": "Query",
      "Type": "String",
      "Description": {
        "zh": "阿里云颁发给用户的访问服务所用的密钥ID。"
      },
      "Required": false,
      "Hidden": false,
      "Example": "",
      "SubParameters": null
    },
    {
      "Name": "AccessKeyId",
      "Position": "Query",
      "Type": "String",
      "Description": {},
      "Required": false,
      "Hidden": false,
      "Example": "",
      "SubParameters": null
    },
    {
      "Name": "Action",
      "Position": "Query",
      "Type": "String",
      "Description": {
        "zh": "系统规定参数，取值：ModifyAccountDescription。"
      },
      "Required": false,
      "Hidden": true,
      "Example": "",
      "SubParameters": null
    },
    {
      "Name": "OwnerId",
      "Position": "Query",
      "Type": "Long",
      "Description": {
        "zh": ""
      },
      "Required": false,
      "Hidden": true,
      "Example": "",
      "SubParameters": null
    },
    {
      "Name": "ResourceOwnerAccount",
      "Position": "Query",
      "Type": "String",
      "Description": {
        "zh": ""
      },
      "Required": false,
      "Hidden": true,
      "Example": "",
      "SubParameters": null
    },
    {
      "Name": "ResourceOwnerId",
      "Position": "Query",
      "Type": "Long",
      "Description": {
        "zh": ""
      },
      "Required": false,
      "Hidden": true,
      "Example": "",
      "SubParameters": null
    },
    {
      "Name": "DBInstanceId",
      "Position": "Query",
      "Type": "String",
      "Description": {
        "zh": "实例名。"
      },
      "Required": true,
      "Hidden": false,
      "Example": "",
      "SubParameters": null
    },
    {
      "Name": "AccountName",
      "Position": "Query",
      "Type": "String",
      "Description": {
        "zh": "操作账号，需惟一性检查，由小写字母，数字、下划线组成，字母开头，长度不超过16个字符。其他非法字符，详见\u003ca href=\"~~26317~~\"\u003e禁用关键字表\u003c/a\u003e。"
      },
      "Required": true,
      "Hidden": false,
      "Example": "",
      "SubParameters": null
    },
    {
      "Name": "AccountDescription",
      "Position": "Query",
      "Type": "String",
      "Description": {
        "zh": "修改账号备注。不能以\u003ccode\u003ehttp://\u003c/code\u003e或\u003ccode\u003ehttps://\u003c/code\u003e开头，要以中文、英文字母开头，可以包含中文、英文字符、“_”、“ -”、数字，长度为2~256个字符。"
      },
      "Required": true,
      "Hidden": false,
      "Example": "",
      "SubParameters": null
    },
    {
      "Name": "OwnerAccount",
      "Position": "Query",
      "Type": "String",
      "Description": {
        "zh": "用户主账号。"
      },
      "Required": false,
      "Hidden": true,
      "Example": "",
      "SubParameters": null
    }
  ],
  "Product": null
}