{
  "Name": "NodeProcessCreate",
  "Protocol": "HTTP|HTTPS",
  "Method": "GET",
  "Description": {},
  "Parameters": [
    {
      "Name": "InstanceId",
      "Position": "Query",
      "Type": "String",
      "Description": {},
      "Required": true,
      "Hidden": false,
      "Example": "",
      "SubParameters": null
    },
    {
      "Name": "Name",
      "Position": "Query",
      "Type": "String",
      "Description": {},
      "Required": false,
      "Hidden": false,
      "Example": "",
      "SubParameters": null
    },
    {
      "Name": "ProcessName",
      "Position": "Query",
      "Type": "String",
      "Description": {},
      "Required": false,
      "Hidden": false,
      "Example": "",
      "SubParameters": null
    },
    {
      "Name": "ProcessUser",
      "Position": "Query",
      "Type": "String",
      "Description": {},
      "Required": false,
      "Hidden": false,
      "Example": "",
      "SubParameters": null
    },
    {
      "Name": "Command",
      "Position": "Query",
      "Type": "String",
      "Description": {},
      "Required": false,
      "Hidden": false,
      "Example": "",
      "SubParameters": null
    }
  ],
  "Product": null
}